MANIFEST.in
README.txt
setup.py
atreal/__init__.py
atreal/__init__.pyc
atreal.filestorage.common.egg-info/PKG-INFO
atreal.filestorage.common.egg-info/SOURCES.txt
atreal.filestorage.common.egg-info/dependency_links.txt
atreal.filestorage.common.egg-info/entry_points.txt
atreal.filestorage.common.egg-info/namespace_packages.txt
atreal.filestorage.common.egg-info/not-zip-safe
atreal.filestorage.common.egg-info/requires.txt
atreal.filestorage.common.egg-info/top_level.txt
atreal/filestorage/__init__.py
atreal/filestorage/__init__.pyc
atreal/filestorage/common/__init__.py
atreal/filestorage/common/__init__.pyc
atreal/filestorage/common/annotation.py
atreal/filestorage/common/annotation.pyc
atreal/filestorage/common/configure.zcml
atreal/filestorage/common/dirobj.py
atreal/filestorage/common/fileobj.py
atreal/filestorage/common/interfaces.py
atreal/filestorage/common/interfaces.pyc
atreal/filestorage/common/registry.py
atreal/filestorage/common/registry.pyc
atreal/filestorage/common/tests.py
atreal/filestorage/common/version.txt
atreal/filestorage/common/zodbstore.py
atreal/filestorage/common/zodbstore.pyc
docs/HISTORY.txt
docs/INSTALL.txt
docs/LICENSE.GPL
docs/LICENSE.txt