Metadata-Version: 1.0
Name: atreal.filestorage.common
Version: 1.0.1
Summary: Defines a common API to handle file objects independently of storage
Home-page: http://www.atreal.fr/
Author: atReal
Author-email: contact@atreal.fr
License: GPL
Keywords: plone atreal file blob
Platform: UNKNOWN
Classifier: Framework :: Plone
Classifier: Programming Language :: Python
Classifier: Topic :: Software Development :: Libraries :: Python Modules
